rayon/__init__.py
rayon/__main__.py
rayon/bin/server_env.sh
rayon/bin/server_run.py
rayon/common.py
rayon/config.py
rayon/config_file.py
rayon/etc/alertmanager.yml
rayon/etc/conf.d/server
rayon/etc/nginx/mime.types
rayon/etc/nginx/nginx.conf
rayon/etc/prometheus.yml
rayon/etc/rc.d/server
rayon/etc/redis.conf
rayon/etc/server-conf.sh
rayon/etc/supervisord.conf
rayon/filesystem.py
rayon/logging.py
rayon/static/css/phyd3.min.css
rayon/static/favicon.ico
rayon/static/js/phyd3.min.js
rayon/templates/index.html
rayon/test/README.txt
rayon/test/diabetes.txt
rayon/test/email.txt
rayon/test/post_run.sh
rayon/test/rayon_rc
rayon/test/title.txt
rayon/user_conf/server_rc
rayon/var/html/404.html
rayon/var/html/50x.html
rayon/var/html/index.html
rayon-0.0.36.dist-info/entry_points.txt
rayon-0.0.36.dist-info/LICENSE.txt
rayon-0.0.36.dist-info/WHEEL
rayon-0.0.36.dist-info/METADATA
rayon-0.0.36.dist-info/RECORD
