Metadata-Version: 2.1
Name: rayon
Version: 0.0.36
Summary: Web service for ProteinGraphML
Home-page: https://github.com/unmtransinfo/rayon
License: BSD-3-Clause
Keywords: science,biology,machine learning,web services
Author: UNM Translational Informatics
Author-email: datascience.software@salud.unm.edu
Requires-Python: >=3.8.1,<3.10
Classifier: Development Status :: 4 - Beta
Classifier: Environment :: Console
Classifier: Framework :: Flask
Classifier: Intended Audience :: Science/Research
Classifier: License :: OSI Approved :: BSD License
Classifier: Natural Language :: English
Classifier: Operating System :: MacOS :: MacOS X
Classifier: Operating System :: POSIX :: BSD
Classifier: Operating System :: POSIX :: Linux
Classifier: Programming Language :: Python :: 3
Classifier: Programming Language :: Python :: 3.8
Classifier: Programming Language :: Python :: 3.9
Classifier: Topic :: Internet :: WWW/HTTP :: WSGI :: Server
Classifier: Topic :: Scientific/Engineering :: Bio-Informatics
Requires-Dist: Flask_RQ2[cli]
Requires-Dist: PyYAML (>=5.4.1,<6.0.0)
Requires-Dist: XlsxWriter
Requires-Dist: colorama
Requires-Dist: gunicorn
Requires-Dist: healthcheck (>=1.3.3,<2.0.0)
Requires-Dist: matplotlib
Requires-Dist: mysqlclient (>=2.0.3,<3.0.0)
Requires-Dist: networkx
Requires-Dist: openpyxl (>=3.0.7,<4.0.0)
Requires-Dist: pandas
Requires-Dist: pony
Requires-Dist: prometheus_client
Requires-Dist: pyreadr (>=0.4.2,<0.5.0)
Requires-Dist: raven[flask]
Requires-Dist: rq-dashboard
Requires-Dist: sanitize-filename (>=1.2.0,<2.0.0)
Requires-Dist: scikit-learn
Requires-Dist: sh
Requires-Dist: superlance
Requires-Dist: supervisor
Requires-Dist: supervisor-wildcards (>=0.1.3,<0.2.0)
Requires-Dist: xgboost
Requires-Dist: xlrd
Project-URL: Changelog, https://github.com/unmtransinfo/rayon/releases
Project-URL: Documentation, https://rayon.readthedocs.io
Project-URL: Repository, https://github.com/unmtransinfo/rayon
